wopeditor/__init__.py
wopeditor/__main__.py
wopeditor/platform.py
wopeditor/wopeditor.py
wopeditor/woplang.py
wopeditor/wopmods.py
wopeditor/screens/__init__.py
wopeditor/screens/abc.py
wopeditor/screens/abcs.py
wopeditor/screens/calibrate.py
wopeditor/screens/drawing.py
wopeditor/screens/model.py
wopeditor/screens/newdrawing.py
wopeditor/screens/symbol.py
wopeditor/screens/testabc.py
wopeditor/widgets/__init__.py
wopeditor/widgets/drawingarea.py
wopeditor/widgets/drawingpreview.py
wopeditor/widgets/errorpopup.py
wopeditor/widgets/focusbutton.py
wopeditor/widgets/header.py
wopeditor/widgets/labeledtextinput.py
wopeditor/widgets/modelpreview.py
wopeditor/widgets/nicescrollview.py
wopeditor/widgets/sidebar.py
wopeditor-0.1.1.dist-info/LICENSE
wopeditor-0.1.1.dist-info/METADATA
wopeditor-0.1.1.dist-info/WHEEL
wopeditor-0.1.1.dist-info/entry_points.txt
wopeditor-0.1.1.dist-info/top_level.txt
wopeditor-0.1.1.dist-info/RECORD
