Metadata-Version: 2.1
Name: wopeditor
Version: 0.1.1
Summary: Words of Power Editor of TexnoMagic
Home-page: https://github.com/texnoforge/wopeditor/
Author: texnoforge
Author-email: voice@texnoforge.dev
License: UNKNOWN
Project-URL: Bug Tracker, https://github.com/texnoforge/wopeditor/issues
Project-URL: Docs, https://texnoforge.github.io/wopeditor/
Platform: UNKNOWN
Classifier: Programming Language :: Python :: 3
Classifier: License :: OSI Approved :: MIT License
Classifier: Operating System :: OS Independent
Requires-Dist: kivy
Requires-Dist: texnomagic
Requires-Dist: trio
